torchastic/__init__.py
torchastic/stochastic_optim.py
torchastic-0.1.2.dist-info/LICENSE
torchastic-0.1.2.dist-info/METADATA
torchastic-0.1.2.dist-info/WHEEL
torchastic-0.1.2.dist-info/top_level.txt
torchastic-0.1.2.dist-info/RECORD
