Metadata-Version: 2.1
Name: torchastic
Version: 0.1.2
Summary: Stochastic bfloat16 based optimizer library.
Home-page: https://github.com/lodestone-rock/torchastic
Author: Lodestone
Author-email: lodestone.rock@gmail.com
License: UNKNOWN
Platform: UNKNOWN
Classifier: Programming Language :: Python :: 3
Classifier: License :: OSI Approved :: Apache Software License
Classifier: Operating System :: OS Independent
Requires-Python: >=3.8
License-File: LICENSE
